{"name":"A-Fort","desc":"A large fort.","guild":"Aphros","category":"Aphros","width":29,"height":23,"cost":"150,000","rent_cost":100,"rent_upfront":500,"watchtower":0,"settlement_only":1,"map":{"3,1":{"type":"/turf/academy/fence/horizontal/bottom/left"},"4,1":{"type":"/turf/academy/fence/horizontal/bottom/middle"},"5,1":{"type":"/turf/academy/fence/horizontal/bottom/middle"},"6,1":{"type":"/turf/academy/fence/horizontal/bottom/middle"},"7,1":{"type":"/turf/academy/fence/horizontal/bottom/middle"},"8,1":{"type":"/turf/academy/fence/horizontal/bottom/middle"},"9,1":{"type":"/turf/academy/fence/horizontal/bottom/middle"},"10,1":{"type":"/turf/academy/fence/post/left"},"11,1":{"type":"/turf"},"12,1":{"type":"/turf"},"13,1":{"type":"/turf"},"14,1":{"type":"/turf"},"15,1":{"type":"/turf"},"16,1":{"type":"/turf"},"17,1":{"type":"/turf"},"18,1":{"type":"/turf/academy/fence/post/right"},"19,1":{"type":"/turf/academy/fence/horizontal/bottom/middle"},"20,1":{"type":"/turf/academy/fence/horizontal/bottom/middle"},"21,1":{"type":"/turf/academy/fence/horizontal/bottom/middle"},"22,1":{"type":"/turf/academy/fence/horizontal/bottom/middle"},"23,1":{"type":"/turf/academy/fence/horizontal/bottom/middle"},"24,1":{"type":"/turf/academy/fence/horizontal/bottom/middle"},"25,1":{"type":"/turf/academy/fence/horizontal/bottom/right"},"3,2":{"type":"/turf/academy/fence/side/left"},"4,2":{"type":"/turf"},"5,2":{"type":"/turf"},"6,2":{"type":"/turf"},"7,2":{"type":"/turf"},"8,2":{"type":"/turf"},"9,2":{"type":"/turf"},"10,2":{"type":"/turf"},"11,2":{"type":"/turf"},"12,2":{"type":"/turf"},"13,2":{"type":"/turf"},"14,2":{"type":"/turf"},"15,2":{"type":"/turf"},"16,2":{"type":"/turf"},"17,2":{"type":"/turf"},"18,2":{"type":"/turf"},"19,2":{"type":"/turf"},"20,2":{"type":"/turf"},"21,2":{"type":"/turf"},"22,2":{"type":"/turf"},"23,2":{"type":"/turf"},"24,2":{"type":"/turf"},"25,2":{"type":"/turf/academy/fence/side/right"},"3,3":{"type":"/turf/academy/fence/side/left"},"4,3":{"type":"/turf"},"5,3":{"type":"/turf"},"6,3":{"type":"/turf"},"7,3":{"type":"/turf"},"8,3":{"type":"/turf"},"9,3":{"type":"/turf"},"10,3":{"type":"/turf"},"11,3":{"type":"/turf"},"12,3":{"type":"/turf"},"13,3":{"type":"/turf"},"14,3":{"type":"/turf"},"15,3":{"type":"/turf"},"16,3":{"type":"/turf"},"17,3":{"type":"/turf"},"18,3":{"type":"/turf"},"19,3":{"type":"/turf"},"20,3":{"type":"/turf"},"21,3":{"type":"/turf"},"22,3":{"type":"/turf"},"23,3":{"type":"/turf"},"24,3":{"type":"/turf"},"25,3":{"type":"/turf/academy/fence/side/right"},"3,4":{"type":"/turf/academy/fence/side/left"},"4,4":{"type":"/turf"},"5,4":{"type":"/turf"},"6,4":{"type":"/turf"},"7,4":{"type":"/turf"},"8,4":{"type":"/turf"},"9,4":{"type":"/turf"},"10,4":{"type":"/turf"},"11,4":{"type":"/turf/city/railing/left"},"12,4":{"type":"/turf/city/stairs/bottom"},"13,4":{"type":"/turf/city/stairs/bottom"},"14,4":{"type":"/turf/city/stairs/bottom"},"15,4":{"type":"/turf/city/stairs/bottom"},"16,4":{"type":"/turf/city/stairs/bottom"},"17,4":{"type":"/turf/city/railing/right","layer":5},"18,4":{"type":"/turf"},"19,4":{"type":"/turf"},"20,4":{"type":"/turf"},"21,4":{"type":"/turf"},"22,4":{"type":"/turf"},"23,4":{"type":"/turf"},"24,4":{"type":"/turf"},"25,4":{"type":"/turf/academy/fence/side/right"},"3,5":{"type":"/turf/academy/fence/side/left"},"4,5":{"type":"/turf"},"5,5":{"type":"/turf"},"6,5":{"type":"/turf"},"7,5":{"type":"/turf"},"8,5":{"type":"/turf"},"9,5":{"type":"/turf/ColiseumSilver/ColiseumSilver/right/fortysix"},"10,5":{"type":"/turf/village/wall_aphros/bottom"},"11,5":{"type":"/turf/city/railing/left"},"12,5":{"type":"/turf/city/stairs"},"13,5":{"type":"/turf/city/stairs"},"14,5":{"type":"/turf/city/stairs"},"15,5":{"type":"/turf/city/stairs"},"16,5":{"type":"/turf/city/stairs"},"17,5":{"type":"/turf/city/railing/right","layer":5},"18,5":{"type":"/turf/village/wall_aphros/bottom"},"19,5":{"type":"/turf/ColiseumSilver/ColiseumSilver/left/fifty"},"20,5":{"type":"/turf","objects":["/obj/generic_shadow/white"]},"21,5":{"type":"/turf"},"22,5":{"type":"/turf"},"23,5":{"type":"/turf"},"24,5":{"type":"/turf"},"25,5":{"type":"/turf/academy/fence/side/right"},"3,6":{"type":"/turf/academy/fence/side/left"},"4,6":{"type":"/turf"},"5,6":{"type":"/turf"},"6,6":{"type":"/turf"},"7,6":{"type":"/turf"},"8,6":{"type":"/turf"},"9,6":{"type":"/turf/ColiseumSilver/ColiseumSilver/right/fortysix"},"10,6":{"type":"/turf/ColiseumSilver/ColiseumSilver/front/two"},"11,6":{"type":"/turf/city/railing/left"},"12,6":{"type":"/turf/city/stairs"},"13,6":{"type":"/turf/city/stairs"},"14,6":{"type":"/turf/city/stairs"},"15,6":{"type":"/turf/city/stairs"},"16,6":{"type":"/turf/city/stairs"},"17,6":{"type":"/turf/city/railing/right","layer":5},"18,6":{"type":"/turf/ColiseumSilver/ColiseumSilver/front/two"},"19,6":{"type":"/turf/ColiseumSilver/ColiseumSilver/left/fifty"},"20,6":{"type":"/turf","objects":["/obj/generic_shadow/white"]},"21,6":{"type":"/turf"},"22,6":{"type":"/turf"},"23,6":{"type":"/turf"},"24,6":{"type":"/turf"},"25,6":{"type":"/turf/academy/fence/side/right"},"3,7":{"type":"/turf/academy/fence/side/left"},"4,7":{"type":"/turf"},"5,7":{"type":"/turf"},"6,7":{"type":"/turf"},"7,7":{"type":"/turf"},"8,7":{"type":"/turf"},"9,7":{"type":"/turf/city/railing/bottom/left"},"10,7":{"type":"/turf/city/railing/bottom"},"11,7":{"type":"/turf/city/railing/top/right/one"},"12,7":{"type":"/turf/gothic/dungeon/floor"},"13,7":{"type":"/turf/gothic/dungeon/floor"},"14,7":{"type":"/turf/gothic/dungeon/floor"},"15,7":{"type":"/turf/gothic/dungeon/floor"},"16,7":{"type":"/turf/gothic/dungeon/floor"},"17,7":{"type":"/turf/city/railing/top/left/one"},"18,7":{"type":"/turf/city/railing/bottom"},"19,7":{"type":"/turf/city/railing/bottom/right"},"20,7":{"type":"/turf","objects":["/obj/generic_shadow/white"]},"21,7":{"type":"/turf"},"22,7":{"type":"/turf"},"23,7":{"type":"/turf"},"24,7":{"type":"/turf"},"25,7":{"type":"/turf/academy/fence/side/right"},"0,8":{"type":"/turf"},"1,8":{"type":"/turf/village/wall_aphros/bottom_left"},"2,8":{"type":"/turf/village/wall_aphros/bottom"},"3,8":{"type":"/turf/village/wall_aphros/bottom"},"4,8":{"type":"/turf/village/wall_aphros/bottom"},"5,8":{"type":"/turf/village/wall_aphros/bottom_right"},"6,8":{"type":"/turf","objects":["/obj/generic_shadow/white"]},"7,8":{"type":"/turf/ColiseumSilver/ColumnSilver/bottom"},"8,8":{"type":"/turf"},"9,8":{"type":"/turf/city/railing/left"},"10,8":{"type":"/turf/gothic/dungeon/floor"},"11,8":{"type":"/turf/gothic/dungeon/floor"},"12,8":{"type":"/turf/gothic/dungeon/floor"},"13,8":{"type":"/turf/gothic/dungeon/floor"},"14,8":{"type":"/turf/gothic/dungeon/floor"},"15,8":{"type":"/turf/gothic/dungeon/floor"},"16,8":{"type":"/turf/gothic/dungeon/floor"},"17,8":{"type":"/turf/gothic/dungeon/floor"},"18,8":{"type":"/turf/gothic/dungeon/floor"},"19,8":{"type":"/turf/city/railing/right","layer":5},"20,8":{"type":"/turf","objects":["/obj/generic_shadow/white"]},"21,8":{"type":"/turf/ColiseumSilver/ColumnSilver/bottom"},"22,8":{"type":"/turf"},"23,8":{"type":"/turf/village/wall_aphros/bottom_left"},"24,8":{"type":"/turf/village/wall_aphros/bottom"},"25,8":{"type":"/turf/village/wall_aphros/bottom"},"26,8":{"type":"/turf/village/wall_aphros/bottom"},"27,8":{"type":"/turf/village/wall_aphros/bottom_right"},"28,8":{"type":"/turf"},"0,9":{"type":"/turf"},"1,9":{"type":"/turf/village/wall_aphros/middle_left"},"2,9":{"type":"/turf/village/wall_aphros/middle"},"3,9":{"type":"/turf/house/wooden_window","layer":4,"density":1},"4,9":{"type":"/turf/village/wall_aphros/middle"},"5,9":{"type":"/turf/village/wall_aphros/middle_right"},"6,9":{"type":"/turf/village/wall_aphros/bottom","objects":["/obj/generic_shadow/white"]},"7,9":{"type":"/turf/ColiseumSilver/ColumnSilver/middle/one"},"8,9":{"type":"/turf/village/wall_aphros/bottom"},"9,9":{"type":"/turf/city/railing/left"},"10,9":{"type":"/turf/gothic/dungeon/floor","objects":["/obj/generic_shadow/white"]},"11,9":{"type":"/turf/gothic/dungeon/floor","objects":["/obj/generic_shadow/white"]},"12,9":{"type":"/turf/gothic/dungeon/floor","objects":["/obj/generic_shadow/white","/obj/map/village/statue/mage/right"]},"13,9":{"type":"/turf/gothic/dungeon/floor","objects":["/obj/generic_shadow/white"]},"14,9":{"type":"/turf/gothic/dungeon/floor","objects":["/obj/generic_shadow/white"]},"15,9":{"type":"/turf/gothic/dungeon/floor","objects":["/obj/generic_shadow/white"]},"16,9":{"type":"/turf/gothic/dungeon/floor","objects":["/obj/generic_shadow/white","/obj/map/village/statue/mage/left"]},"17,9":{"type":"/turf/gothic/dungeon/floor","objects":["/obj/generic_shadow/white"]},"18,9":{"type":"/turf/gothic/dungeon/floor","objects":["/obj/generic_shadow/white"]},"19,9":{"type":"/turf/city/railing/right","layer":5},"20,9":{"type":"/turf/village/wall_aphros/bottom","objects":["/obj/generic_shadow/white"]},"21,9":{"type":"/turf/ColiseumSilver/ColumnSilver/middle/one"},"22,9":{"type":"/turf/village/wall_aphros/bottom"},"23,9":{"type":"/turf/village/wall_aphros/middle_left"},"24,9":{"type":"/turf/village/wall_aphros/middle"},"25,9":{"type":"/turf/house/wooden_window","layer":4,"density":1},"26,9":{"type":"/turf/village/wall_aphros/middle"},"27,9":{"type":"/turf/village/wall_aphros/middle_right"},"28,9":{"type":"/turf"},"0,10":{"type":"/turf"},"1,10":{"type":"/turf/village/wall_aphros/middle_left"},"2,10":{"type":"/turf/village/wall_aphros/middle"},"3,10":{"type":"/turf/house/wooden_window","layer":9,"density":1},"4,10":{"type":"/turf/village/wall_aphros/middle"},"5,10":{"type":"/turf/village/wall_aphros/middle_right"},"6,10":{"type":"/turf/village/wall_aphros/middle","objects":["/obj/generic_shadow/white"]},"7,10":{"type":"/turf/ColiseumSilver/ColumnSilver/middle/three","objects":["/obj/map/gehenna_castle/Brazier"]},"8,10":{"type":"/turf/village/wall_aphros/middle"},"9,10":{"type":"/turf/city/railing/left"},"10,10":{"type":"/turf/village/wall_aphros/bottom_left"},"11,10":{"type":"/turf/village/wall_aphros/bottom"},"12,10":{"type":"/turf/village/wall_aphros/bottom"},"13,10":{"type":"/turf/village/wall_aphros/bottom","objects":["/obj/ColiseumSilver/GateSilver/black/gate"]},"14,10":{"type":"/turf/village/wall_aphros/bottom","objects":["/Building/Warper/Exterior"]},"15,10":{"type":"/turf/village/wall_aphros/bottom"},"16,10":{"type":"/turf/village/wall_aphros/bottom"},"17,10":{"type":"/turf/village/wall_aphros/bottom"},"18,10":{"type":"/turf/village/wall_aphros/bottom_right"},"19,10":{"type":"/turf/city/railing/right","layer":5,"objects":["/obj/generic_shadow/white"]},"20,10":{"type":"/turf/village/wall_aphros/middle","objects":["/obj/generic_shadow/white"]},"21,10":{"type":"/turf/ColiseumSilver/ColumnSilver/middle/three","objects":["/obj/map/gehenna_castle/Brazier"]},"22,10":{"type":"/turf/village/wall_aphros/middle"},"23,10":{"type":"/turf/village/wall_aphros/middle_left"},"24,10":{"type":"/turf/village/wall_aphros/middle"},"25,10":{"type":"/turf/house/wooden_window","layer":9,"density":1},"26,10":{"type":"/turf/village/wall_aphros/middle"},"27,10":{"type":"/turf/village/wall_aphros/middle_right"},"28,10":{"type":"/turf"},"0,11":{"type":"/turf"},"1,11":{"type":"/turf/village/wall_aphros/middle_left"},"2,11":{"type":"/turf/village/wall_aphros/middle"},"3,11":{"type":"/turf/house/wooden_window","layer":4,"density":1},"4,11":{"type":"/turf/village/wall_aphros/middle"},"5,11":{"type":"/turf/village/wall_aphros/middle_right"},"6,11":{"type":"/turf/village/wall_aphros/middle","objects":["/obj/generic_shadow/white"]},"7,11":{"type":"/turf/village/wall_aphros/middle"},"8,11":{"type":"/turf/village/wall_aphros/middle"},"9,11":{"type":"/turf/village/roof_aphros/left_7"},"10,11":{"type":"/turf/village/roof_aphros/left_4"},"11,11":{"type":"/turf/village/wall_aphros/middle"},"12,11":{"type":"/turf/village/wall_aphros/middle"},"13,11":{"type":"/turf/village/wall_aphros/middle"},"14,11":{"type":"/turf/village/wall_aphros/middle"},"15,11":{"type":"/turf/village/wall_aphros/middle"},"16,11":{"type":"/turf/village/wall_aphros/middle"},"17,11":{"type":"/turf/village/wall_aphros/middle"},"18,11":{"type":"/turf/village/roof_aphros/right_4"},"19,11":{"type":"/turf/village/roof_aphros/right_7","layer":7,"objects":["/obj/generic_shadow/white"]},"20,11":{"type":"/turf/village/wall_aphros/middle","objects":["/obj/generic_shadow/white"]},"21,11":{"type":"/turf/village/wall_aphros/middle"},"22,11":{"type":"/turf/village/wall_aphros/middle"},"23,11":{"type":"/turf/village/wall_aphros/middle_left"},"24,11":{"type":"/turf/village/wall_aphros/middle"},"25,11":{"type":"/turf/house/wooden_window","layer":4,"density":1},"26,11":{"type":"/turf/village/wall_aphros/middle"},"27,11":{"type":"/turf/village/wall_aphros/middle_right"},"28,11":{"type":"/turf"},"0,12":{"type":"/turf/village/roof_aphros/left_7","density":0,"objects":["/obj/map/noDenseMarker"]},"1,12":{"type":"/turf/village/roof_aphros/left_4"},"2,12":{"type":"/turf/village/wall_aphros/middle"},"3,12":{"type":"/turf/house/wooden_window","layer":9,"density":1},"4,12":{"type":"/turf/village/wall_aphros/middle"},"5,12":{"type":"/turf/village/roof_aphros/right_4"},"6,12":{"type":"/turf/village/roof_aphros/right_7","layer":7,"objects":["/obj/generic_shadow/white"]},"7,12":{"type":"/turf/ColiseumSilver/ColiseumSilver/front/two"},"8,12":{"type":"/turf/ColiseumSilver/ColiseumSilver/front/two"},"9,12":{"type":"/turf/village/roof_aphros/left_6","layer":7},"10,12":{"type":"/turf/village/roof_aphros/left_1"},"11,12":{"type":"/turf/village/roof_aphros/left_4"},"12,12":{"type":"/turf/village/wall_aphros/middle"},"13,12":{"type":"/turf/village/wall_aphros/middle"},"14,12":{"type":"/turf/house/wooden_window","layer":4,"density":1},"15,12":{"type":"/turf/village/wall_aphros/middle"},"16,12":{"type":"/turf/village/wall_aphros/middle"},"17,12":{"type":"/turf/village/roof_aphros/right_4"},"18,12":{"type":"/turf/village/roof_aphros/right_1"},"19,12":{"type":"/turf/village/roof_aphros/right_6","layer":3,"objects":["/obj/generic_shadow/white"]},"20,12":{"type":"/turf/ColiseumSilver/ColiseumSilver/front/two","objects":["/obj/generic_shadow/white"]},"21,12":{"type":"/turf/ColiseumSilver/ColiseumSilver/front/two"},"22,12":{"type":"/turf/village/roof_aphros/left_7"},"23,12":{"type":"/turf/village/roof_aphros/left_4"},"24,12":{"type":"/turf/village/wall_aphros/middle"},"25,12":{"type":"/turf/house/wooden_window","layer":9,"density":1},"26,12":{"type":"/turf/village/wall_aphros/middle"},"27,12":{"type":"/turf/village/roof_aphros/right_4"},"28,12":{"type":"/turf/village/roof_aphros/right_7","layer":7,"density":0,"objects":["/obj/map/noDenseMarker"]},"0,13":{"type":"/turf/village/roof_aphros/left_6","density":0,"objects":["/obj/map/noDenseMarker"]},"1,13":{"type":"/turf/village/roof_aphros/left_1"},"2,13":{"type":"/turf/village/roof_aphros/left_4"},"3,13":{"type":"/turf/village/wall_aphros/middle"},"4,13":{"type":"/turf/village/roof_aphros/right_4"},"5,13":{"type":"/turf/village/roof_aphros/right_1"},"6,13":{"type":"/turf/village/roof_aphros/right_6","layer":3,"objects":["/obj/generic_shadow/white"]},"7,13":{"type":"/turf/city/railing/bottom"},"8,13":{"type":"/turf/city/railing/bottom"},"9,13":{"type":"/turf/village/roof_aphros/left_6","layer":7},"10,13":{"type":"/turf/village/roof_aphros/left_2"},"11,13":{"type":"/turf/village/roof_aphros/left_1"},"12,13":{"type":"/turf/village/roof_aphros/left_4"},"13,13":{"type":"/turf/village/wall_aphros/middle"},"14,13":{"type":"/turf/house/wooden_window","layer":9,"density":1},"15,13":{"type":"/turf/village/wall_aphros/middle"},"16,13":{"type":"/turf/village/roof_aphros/right_4"},"17,13":{"type":"/turf/village/roof_aphros/right_1"},"18,13":{"type":"/turf/village/roof_aphros/right_2"},"19,13":{"type":"/turf/village/roof_aphros/right_6","layer":3,"objects":["/obj/generic_shadow/white"]},"20,13":{"type":"/turf/city/railing/bottom","objects":["/obj/generic_shadow/white"]},"21,13":{"type":"/turf/city/railing/bottom"},"22,13":{"type":"/turf/village/roof_aphros/left_6","layer":7},"23,13":{"type":"/turf/village/roof_aphros/left_1"},"24,13":{"type":"/turf/village/roof_aphros/left_4"},"25,13":{"type":"/turf/village/wall_aphros/middle"},"26,13":{"type":"/turf/village/roof_aphros/right_4"},"27,13":{"type":"/turf/village/roof_aphros/right_1"},"28,13":{"type":"/turf/village/roof_aphros/right_6","layer":3,"density":0,"objects":["/obj/map/noDenseMarker"]},"0,14":{"type":"/turf/village/roof_aphros/left_6","layer":7,"density":0,"objects":["/obj/map/noDenseMarker"]},"1,14":{"type":"/turf/village/roof_aphros/left_2"},"2,14":{"type":"/turf/village/roof_aphros/left_1"},"3,14":{"type":"/turf/village/roof_aphros/left_4"},"4,14":{"type":"/turf/village/roof_aphros/right_1"},"5,14":{"type":"/turf/village/roof_aphros/right_2"},"6,14":{"type":"/turf/village/roof_aphros/right_6","layer":3,"objects":["/obj/generic_shadow/white"]},"7,14":{"type":"/turf/gothic/dungeon/floor","objects":["/obj/generic_shadow/white"]},"8,14":{"type":"/turf/gothic/dungeon/floor","objects":["/obj/generic_shadow/white"]},"9,14":{"type":"/turf/village/roof_aphros/left_6","layer":7,"objects":["/obj/generic_shadow/white"]},"10,14":{"type":"/turf/village/roof_aphros/left_2"},"11,14":{"type":"/turf/village/roof_aphros/left_2"},"12,14":{"type":"/turf/village/roof_aphros/left_1"},"13,14":{"type":"/turf/village/roof_aphros/left_4"},"14,14":{"type":"/turf/village/aphros_extra/windowbig_2"},"15,14":{"type":"/turf/village/roof_aphros/right_4"},"16,14":{"type":"/turf/village/roof_aphros/right_1"},"17,14":{"type":"/turf/village/roof_aphros/right_2"},"18,14":{"type":"/turf/village/roof_aphros/right_2"},"19,14":{"type":"/turf/village/roof_aphros/right_6","layer":3,"objects":["/obj/generic_shadow/white","/obj/generic_shadow/white"]},"20,14":{"type":"/turf/gothic/dungeon/floor","objects":["/obj/generic_shadow/white","/obj/generic_shadow/white"]},"21,14":{"type":"/turf/gothic/dungeon/floor","objects":["/obj/generic_shadow/white"]},"22,14":{"type":"/turf/village/roof_aphros/left_6","layer":7},"23,14":{"type":"/turf/village/roof_aphros/left_2"},"24,14":{"type":"/turf/village/roof_aphros/left_1"},"25,14":{"type":"/turf/village/roof_aphros/left_4"},"26,14":{"type":"/turf/village/roof_aphros/right_1"},"27,14":{"type":"/turf/village/roof_aphros/right_2"},"28,14":{"type":"/turf/village/roof_aphros/right_6","layer":3,"density":0,"objects":["/obj/map/noDenseMarker"]},"0,15":{"type":"/turf/village/roof_aphros/left_5","density":0,"objects":["/obj/map/noDenseMarker"]},"1,15":{"type":"/turf/village/roof_aphros/left_2"},"2,15":{"type":"/turf/village/roof_aphros/left_2"},"3,15":{"type":"/turf/village/roof_aphros/center_1"},"4,15":{"type":"/turf/village/roof_aphros/right_2"},"5,15":{"type":"/turf/village/roof_aphros/right_2"},"6,15":{"type":"/turf/village/roof_aphros/right_5","layer":7,"density":0,"objects":["/obj/generic_shadow/white"]},"7,15":{"type":"/turf/village/horizontal_roof_aphros/bottom_right"},"8,15":{"type":"/turf/city/railing/bottom"},"9,15":{"type":"/turf/village/roof_aphros/left_6","layer":7},"10,15":{"type":"/turf/village/roof_aphros/left_2"},"11,15":{"type":"/turf/village/roof_aphros/left_2"},"12,15":{"type":"/turf/village/roof_aphros/left_2"},"13,15":{"type":"/turf/village/roof_aphros/left_1"},"14,15":{"type":"/turf/village/roof_aphros/left_4"},"15,15":{"type":"/turf/village/roof_aphros/right_1"},"16,15":{"type":"/turf/village/roof_aphros/right_2"},"17,15":{"type":"/turf/village/roof_aphros/right_2"},"18,15":{"type":"/turf/village/roof_aphros/right_2"},"19,15":{"type":"/turf/village/roof_aphros/right_6","layer":3,"objects":["/obj/generic_shadow/white"]},"20,15":{"type":"/turf/city/railing/bottom"},"21,15":{"type":"/turf/village/horizontal_roof_aphros/bottom_left"},"22,15":{"type":"/turf/village/roof_aphros/left_5","layer":7,"density":0},"23,15":{"type":"/turf/village/roof_aphros/left_2"},"24,15":{"type":"/turf/village/roof_aphros/left_2"},"25,15":{"type":"/turf/village/roof_aphros/center_1"},"26,15":{"type":"/turf/village/roof_aphros/right_2"},"27,15":{"type":"/turf/village/roof_aphros/right_2"},"28,15":{"type":"/turf/village/roof_aphros/right_5","layer":7,"density":0,"objects":["/obj/map/noDenseMarker"]},"0,16":{"type":"/turf"},"1,16":{"type":"/turf/village/roof_aphros/left_3","density":0,"objects":["/obj/map/noDenseMarker"]},"2,16":{"type":"/turf/village/roof_aphros/left_2"},"3,16":{"type":"/turf/village/roof_aphros/center_2"},"4,16":{"type":"/turf/village/roof_aphros/right_2"},"5,16":{"type":"/turf/village/roof_aphros/right_3","layer":7},"6,16":{"type":"/turf/village/horizontal_roof_aphros/fill"},"7,16":{"type":"/turf/village/horizontal_roof_aphros/right","density":0,"objects":["/obj/map/noDenseMarker"]},"8,16":{"type":"/turf"},"9,16":{"type":"/turf/village/roof_aphros/left_6","layer":7,"density":0,"objects":["/obj/map/noDenseMarker"]},"10,16":{"type":"/turf/village/horizontal_roof_aphros/bottom_left"},"11,16":{"type":"/turf/village/roof_aphros/left_3"},"12,16":{"type":"/turf/village/roof_aphros/left_2"},"13,16":{"type":"/turf/village/roof_aphros/left_2"},"14,16":{"type":"/turf/village/roof_aphros/center_1"},"15,16":{"type":"/turf/village/roof_aphros/right_2"},"16,16":{"type":"/turf/village/roof_aphros/right_2"},"17,16":{"type":"/turf/village/roof_aphros/right_3"},"18,16":{"type":"/turf/village/horizontal_roof_aphros/bottom_right"},"19,16":{"type":"/turf/village/roof_aphros/right_6","layer":3,"density":0,"objects":["/obj/map/noDenseMarker"]},"20,16":{"type":"/turf"},"21,16":{"type":"/turf/village/horizontal_roof_aphros/left","density":0,"objects":["/obj/map/noDenseMarker"]},"22,16":{"type":"/turf/village/horizontal_roof_aphros/fill"},"23,16":{"type":"/turf/village/roof_aphros/left_3","layer":7},"24,16":{"type":"/turf/village/roof_aphros/left_2"},"25,16":{"type":"/turf/village/roof_aphros/center_2"},"26,16":{"type":"/turf/village/roof_aphros/right_2"},"27,16":{"type":"/turf/village/roof_aphros/right_3","density":0,"objects":["/obj/map/noDenseMarker"]},"28,16":{"type":"/turf"},"0,17":{"type":"/turf"},"1,17":{"type":"/turf"},"2,17":{"type":"/turf/village/roof_aphros/left_3","density":0,"objects":["/obj/map/noDenseMarker"]},"3,17":{"type":"/turf/village/roof_aphros/center_2"},"4,17":{"type":"/turf/village/roof_aphros/right_3","layer":7},"5,17":{"type":"/turf/village/horizontal_roof_aphros/fill"},"6,17":{"type":"/turf/village/horizontal_roof_aphros/fill"},"7,17":{"type":"/turf/village/horizontal_roof_aphros/right","density":0,"objects":["/obj/map/noDenseMarker"]},"8,17":{"type":"/turf"},"9,17":{"type":"/turf/village/roof_aphros/left_5","density":0,"objects":["/obj/map/noDenseMarker"]},"10,17":{"type":"/turf/village/horizontal_roof_aphros/left"},"11,17":{"type":"/turf/village/horizontal_roof_aphros/fill"},"12,17":{"type":"/turf/village/roof_aphros/left_3","layer":7},"13,17":{"type":"/turf/village/roof_aphros/left_2"},"14,17":{"type":"/turf/village/roof_aphros/center_2"},"15,17":{"type":"/turf/village/roof_aphros/right_2"},"16,17":{"type":"/turf/village/roof_aphros/right_3","layer":7},"17,17":{"type":"/turf/village/horizontal_roof_aphros/fill"},"18,17":{"type":"/turf/village/horizontal_roof_aphros/right"},"19,17":{"type":"/turf/village/roof_aphros/right_5","density":0,"objects":["/obj/map/noDenseMarker"]},"20,17":{"type":"/turf"},"21,17":{"type":"/turf/village/horizontal_roof_aphros/left","density":0,"objects":["/obj/map/noDenseMarker"]},"22,17":{"type":"/turf/village/horizontal_roof_aphros/fill"},"23,17":{"type":"/turf/village/horizontal_roof_aphros/fill"},"24,17":{"type":"/turf/village/roof_aphros/left_3","layer":7},"25,17":{"type":"/turf/village/roof_aphros/center_2"},"26,17":{"type":"/turf/village/roof_aphros/right_3","density":0,"objects":["/obj/map/noDenseMarker"]},"27,17":{"type":"/turf"},"28,17":{"type":"/turf"},"0,18":{"type":"/turf"},"1,18":{"type":"/turf"},"2,18":{"type":"/turf"},"3,18":{"type":"/turf/village/roof_aphros/center_3","layer":7,"density":0,"objects":["/obj/map/noDenseMarker"]},"4,18":{"type":"/turf/village/horizontal_roof_aphros/top_fill","density":0,"objects":["/obj/map/noDenseMarker"]},"5,18":{"type":"/turf/village/horizontal_roof_aphros/top_fill","density":0,"objects":["/obj/map/noDenseMarker"]},"6,18":{"type":"/turf/village/horizontal_roof_aphros/top_fill","density":0,"objects":["/obj/map/noDenseMarker"]},"7,18":{"type":"/turf/village/horizontal_roof_aphros/top_right","density":0,"objects":["/obj/map/noDenseMarker"]},"8,18":{"type":"/turf"},"9,18":{"type":"/turf"},"10,18":{"type":"/turf/village/horizontal_roof_aphros/left","density":0,"objects":["/obj/map/noDenseMarker"]},"11,18":{"type":"/turf/village/horizontal_roof_aphros/fill"},"12,18":{"type":"/turf/village/horizontal_roof_aphros/fill"},"13,18":{"type":"/turf/village/roof_aphros/left_3","layer":7},"14,18":{"type":"/turf/village/roof_aphros/center_2"},"15,18":{"type":"/turf/village/roof_aphros/right_3","layer":7},"16,18":{"type":"/turf/village/horizontal_roof_aphros/fill"},"17,18":{"type":"/turf/village/horizontal_roof_aphros/fill"},"18,18":{"type":"/turf/village/horizontal_roof_aphros/right","density":0,"objects":["/obj/map/noDenseMarker"]},"19,18":{"type":"/turf"},"20,18":{"type":"/turf"},"21,18":{"type":"/turf/village/horizontal_roof_aphros/top_left","density":0,"objects":["/obj/map/noDenseMarker"]},"22,18":{"type":"/turf/village/horizontal_roof_aphros/top_fill","density":0,"objects":["/obj/map/noDenseMarker"]},"23,18":{"type":"/turf/village/horizontal_roof_aphros/top_fill","density":0,"objects":["/obj/map/noDenseMarker"]},"24,18":{"type":"/turf/village/horizontal_roof_aphros/top_fill","density":0,"objects":["/obj/map/noDenseMarker"]},"25,18":{"type":"/turf/village/roof_aphros/center_3","layer":7,"density":0,"objects":["/obj/map/noDenseMarker"]},"26,18":{"type":"/turf"},"27,18":{"type":"/turf"},"28,18":{"type":"/turf"},"0,19":{"type":"/turf"},"1,19":{"type":"/turf"},"2,19":{"type":"/turf"},"3,19":{"type":"/turf"},"4,19":{"type":"/turf"},"5,19":{"type":"/turf"},"6,19":{"type":"/turf"},"7,19":{"type":"/turf"},"8,19":{"type":"/turf"},"9,19":{"type":"/turf"},"10,19":{"type":"/turf/village/horizontal_roof_aphros/top_left","density":0,"objects":["/obj/map/noDenseMarker"]},"11,19":{"type":"/turf/village/horizontal_roof_aphros/top_fill","density":0,"objects":["/obj/map/noDenseMarker"]},"12,19":{"type":"/turf/village/horizontal_roof_aphros/top_fill"},"13,19":{"type":"/turf/village/horizontal_roof_aphros/top_fill"},"14,19":{"type":"/turf/village/roof_aphros/center_3","layer":7},"15,19":{"type":"/turf/village/horizontal_roof_aphros/top_fill"},"16,19":{"type":"/turf/village/horizontal_roof_aphros/top_fill"},"17,19":{"type":"/turf/village/horizontal_roof_aphros/top_fill","density":0,"objects":["/obj/map/noDenseMarker"]},"18,19":{"type":"/turf/village/horizontal_roof_aphros/top_right","density":0,"objects":["/obj/map/noDenseMarker"]},"19,19":{"type":"/turf"},"20,19":{"type":"/turf"},"21,19":{"type":"/turf"},"22,19":{"type":"/turf"},"23,19":{"type":"/turf"},"24,19":{"type":"/turf"},"25,19":{"type":"/turf"},"26,19":{"type":"/turf"},"27,19":{"type":"/turf"},"28,19":{"type":"/turf"},"0,20":{"type":"/turf"},"1,20":{"type":"/turf"},"2,20":{"type":"/turf"},"3,20":{"type":"/turf"},"4,20":{"type":"/turf"},"5,20":{"type":"/turf"},"6,20":{"type":"/turf"},"7,20":{"type":"/turf"},"8,20":{"type":"/turf"},"9,20":{"type":"/turf"},"10,20":{"type":"/turf"},"11,20":{"type":"/turf"},"12,20":{"type":"/turf/village/roof_aphros/left_3","density":0,"objects":["/obj/map/noDenseMarker"]},"13,20":{"type":"/turf/village/roof_aphros/left_2"},"14,20":{"type":"/turf/village/roof_aphros/center_2"},"15,20":{"type":"/turf/village/roof_aphros/right_2"},"16,20":{"type":"/turf/village/roof_aphros/right_3","density":0,"objects":["/obj/map/noDenseMarker"]},"17,20":{"type":"/turf"},"18,20":{"type":"/turf"},"19,20":{"type":"/turf"},"20,20":{"type":"/turf"},"21,20":{"type":"/turf"},"22,20":{"type":"/turf"},"23,20":{"type":"/turf"},"24,20":{"type":"/turf"},"25,20":{"type":"/turf"},"26,20":{"type":"/turf"},"27,20":{"type":"/turf"},"28,20":{"type":"/turf"},"0,21":{"type":"/turf"},"1,21":{"type":"/turf"},"2,21":{"type":"/turf"},"3,21":{"type":"/turf"},"4,21":{"type":"/turf"},"5,21":{"type":"/turf"},"6,21":{"type":"/turf"},"7,21":{"type":"/turf"},"8,21":{"type":"/turf"},"9,21":{"type":"/turf"},"10,21":{"type":"/turf"},"11,21":{"type":"/turf"},"12,21":{"type":"/turf"},"13,21":{"type":"/turf/village/roof_aphros/left_3","density":0,"objects":["/obj/map/noDenseMarker"]},"14,21":{"type":"/turf/village/roof_aphros/center_2","density":0,"objects":["/obj/map/noDenseMarker"]},"15,21":{"type":"/turf/village/roof_aphros/right_3","density":0,"objects":["/obj/map/noDenseMarker"]},"16,21":{"type":"/turf"},"17,21":{"type":"/turf"},"18,21":{"type":"/turf"},"19,21":{"type":"/turf"},"20,21":{"type":"/turf"},"21,21":{"type":"/turf"},"22,21":{"type":"/turf"},"23,21":{"type":"/turf"},"24,21":{"type":"/turf"},"25,21":{"type":"/turf"},"26,21":{"type":"/turf"},"27,21":{"type":"/turf"},"28,21":{"type":"/turf"},"0,22":{"type":"/turf"},"1,22":{"type":"/turf"},"2,22":{"type":"/turf"},"3,22":{"type":"/turf"},"4,22":{"type":"/turf"},"5,22":{"type":"/turf"},"6,22":{"type":"/turf"},"7,22":{"type":"/turf"},"8,22":{"type":"/turf"},"9,22":{"type":"/turf"},"10,22":{"type":"/turf"},"11,22":{"type":"/turf"},"12,22":{"type":"/turf"},"13,22":{"type":"/turf"},"14,22":{"type":"/turf/village/roof_aphros/center_3","density":0,"objects":["/obj/map/noDenseMarker"]},"15,22":{"type":"/turf"},"16,22":{"type":"/turf"},"17,22":{"type":"/turf"},"18,22":{"type":"/turf"},"19,22":{"type":"/turf"},"20,22":{"type":"/turf"},"21,22":{"type":"/turf"},"22,22":{"type":"/turf"},"23,22":{"type":"/turf"},"24,22":{"type":"/turf"},"25,22":{"type":"/turf"},"26,22":{"type":"/turf"},"27,22":{"type":"/turf"},"28,22":{"type":"/turf"}}}
